[
  {
    "id": 1,
    "name": "Quinoa Bowl",
    "description": "Veggies & quinoa",
    "price": 9.99,
    "tags": ["Vegan", "Gluten Free"],
    "spiciness": 2,
    "sweetness": 1,
    "saltLevel": "less",
    "category": "Breakfast",
    "imageUrl": "/assets/images/quinoa-bowl.jpg"
  },
  {
    "id": 2,
    "name": "Chicken Wrap",
    "description": "Grilled chicken wrap",
    "price": 8.49,
    "tags": ["Non Vegetarian"],
    "spiciness": 6,
    "sweetness": 1,
    "saltLevel": "medium",
    "category": "Snacks",
    "imageUrl": "/assets/images/chicken-wrap.jpg"
  },
  {
    "id": 3,
    "name": "Avocado Toast",
    "description": "Avocado on multigrain bread",
    "price": 6.5,
    "tags": ["Vegetarian"],
    "spiciness": 0,
    "sweetness": 2,
  "saltLevel": "less",
    "category": "Breakfast",
    "imageUrl": "/assets/images/avocado-toast.jpg"
  }
]
